zorg_edison/adaptor.py
zorg_edison/__init__.py
tests/mock_mraa.py
tests/__init__.py
tests/test_adaptor.py
zorg_edison-0.0.2.dist-info/RECORD
zorg_edison-0.0.2.dist-info/top_level.txt
zorg_edison-0.0.2.dist-info/metadata.json
zorg_edison-0.0.2.dist-info/zip-safe
zorg_edison-0.0.2.dist-info/METADATA
zorg_edison-0.0.2.dist-info/DESCRIPTION.rst
zorg_edison-0.0.2.dist-info/WHEEL
