Metadata-Version: 2.0
Name: zorg-edison
Version: 0.0.2
Summary: Intel Edison adapters for the Zorg framework.
Home-page: https://github.com/zorg/zorg-edison
Author: Zorg Group
Author-email: gunthercx@gmail.com
License: MIT
Keywords: zorg,intel,edison
Platform: any
Classifier: Development Status :: 4 - Beta
Classifier: Intended Audience :: Developers
Classifier: License :: OSI Approved :: BSD License
Classifier: Environment :: Console
Classifier: Environment :: Web Environment
Classifier: Operating System :: OS Independent
Classifier: Programming Language :: Python
Classifier: Programming Language :: Python :: 2
Classifier: Programming Language :: Python :: 2.7
Classifier: Programming Language :: Python :: 3
Classifier: Programming Language :: Python :: 3.3
Classifier: Programming Language :: Python :: 3.4
Requires-Dist: zorg (==0.0.1)
